<gmd:MD_Metadata xmlns:gmd="http://www.isotc211.org/2005/gmd"
  xmlns="http://www.isotc211.org/2005/gmd" xmlns:gco="http://www.isotc211.org/2005/gco"
  xmlns:gts="http://www.isotc211.org/2005/gts" xmlns:srv="http://www.isotc211.org/2005/srv"
  xmlns:gml="http://www.opengis.net/gml" xmlns:gmx="http://www.isotc211.org/2005/gmx"
  xmlns:xlink="http://www.w3.org/1999/xlink" xmlns:xsi="http://www.w3.org/2001/XMLSchema-instance"
  xsi:schemaLocation="http://www.isotc211.org/2005/gmd http://www.northwestknowledge.net/iso/xsd/schema.xsd">
  <gmd:fileIdentifier>
    <gco:CharacterString>nkn:d986d1f3-89c1-4c76-9946-eb750f3e921a</gco:CharacterString>
  </gmd:fileIdentifier>
  <gmd:language>
    <gmd:LanguageCode codeList="http://www.loc.gov/standards/iso639-2/php/code_list.php" codeListValue="eng" codeSpace="ISO639-2">eng</gmd:LanguageCode>
  </gmd:language>
  <gmd:characterSet>
    <gmd:MD_CharacterSetCode codeList="http://www.isotc211.org/2005/resources/Codelist/gmxCodelists.xml#MD_CharacterSetCode" codeListValue="utf8" codeSpace="ISOTC211/19115">utf8</gmd:MD_CharacterSetCode>
  </gmd:characterSet>
  <gmd:hierarchyLevel>
    <gmd:MD_ScopeCode codeList="http://www.isotc211.org/2005/resources/Codelist/gmxCodelists.xml#MD_ScopeCode" codeListValue="dataset" codeSpace="ISOTC211/19115">dataset</gmd:MD_ScopeCode>
  </gmd:hierarchyLevel>
  <gmd:hierarchyLevelName>
    <gco:CharacterString>dataset</gco:CharacterString>
  </gmd:hierarchyLevelName>
  <gmd:contact>
    <gmd:CI_ResponsibleParty>
      <gmd:individualName>
        <gco:CharacterString>Mark Solomon</gco:CharacterString>
      </gmd:individualName>
      <gmd:organisationName>
        <gco:CharacterString>Idaho Water Resources Research Institute</gco:CharacterString>
      </gmd:organisationName>
      <gmd:positionName>
        <gco:CharacterString>Water Research Scientist</gco:CharacterString>
      </gmd:positionName>
      <gmd:contactInfo>
        <gmd:CI_Contact>
          <gmd:phone>
            <gmd:CI_Telephone>
              <gmd:voice>
                <gco:CharacterString>(208) 664-7027</gco:CharacterString>
              </gmd:voice>
            </gmd:CI_Telephone>
          </gmd:phone>
          <gmd:address>
            <gmd:CI_Address>
              <gmd:electronicMailAddress>
                <gco:CharacterString>msolomon@uidaho.edu</gco:CharacterString>
              </gmd:electronicMailAddress>
            </gmd:CI_Address>
          </gmd:address>
        </gmd:CI_Contact>
      </gmd:contactInfo>
      <gmd:role>
        <gmd:CI_RoleCode codeList="http://www.isotc211.org/2005/resources/Codelist/gmxCodelists.xml#CI_RoleCode" codeListValue="pointOfContact" codeSpace="ISOTC211/19115">pointOfContact</gmd:CI_RoleCode>
      </gmd:role>
    </gmd:CI_ResponsibleParty>
  </gmd:contact>
  <gmd:contact>
    <gmd:CI_ResponsibleParty>
      <gmd:individualName>
        <gco:CharacterString>Michael Foushee</gco:CharacterString>
      </gmd:individualName>
      <gmd:organisationName>
        <gco:CharacterString>Idaho Water Resources Research Institute</gco:CharacterString>
      </gmd:organisationName>
      <gmd:positionName>
        <gco:CharacterString>GIS Analyst</gco:CharacterString>
      </gmd:positionName>
      <gmd:contactInfo>
        <gmd:CI_Contact>
          <gmd:address>
            <gmd:CI_Address>
              <gmd:electronicMailAddress>
                <gco:CharacterString>fous4241@vandals.uidaho.edu</gco:CharacterString>
              </gmd:electronicMailAddress>
            </gmd:CI_Address>
          </gmd:address>
        </gmd:CI_Contact>
      </gmd:contactInfo>
      <gmd:role>
        <gmd:CI_RoleCode codeList="http://www.isotc211.org/2005/resources/Codelist/gmxCodelists.xml#CI_RoleCode" codeListValue="author" codeSpace="ISOTC211/19115">author</gmd:CI_RoleCode>
      </gmd:role>
    </gmd:CI_ResponsibleParty>
  </gmd:contact>
  <gmd:dateStamp>
    <gco:Date>2015-04-22</gco:Date>
  </gmd:dateStamp>
  <gmd:metadataStandardName>
    <gco:CharacterString>ISO 19139 Geographic Information - Metadata - Implementation
      Specification</gco:CharacterString>
  </gmd:metadataStandardName>
  <gmd:metadataStandardVersion>
    <gco:CharacterString>2007</gco:CharacterString>
  </gmd:metadataStandardVersion>
  <gmd:dataSetURI>
    <gco:CharacterString>d986d1f3-89c1-4c76-9946-eb750f3e921a</gco:CharacterString>
  </gmd:dataSetURI>
  <gmd:identificationInfo>
    <gmd:MD_DataIdentification>
      <gmd:citation>
        <gmd:CI_Citation>
          <gmd:title>
            <gco:CharacterString>Rathdrum Prairie Aquifer Reasonably Anticipated Future Need Study
              Data</gco:CharacterString>
          </gmd:title>
          <gmd:date>
            <gmd:CI_Date>
              <gmd:date>
                <gco:Date>2014-10-01</gco:Date>
              </gmd:date>
              <gmd:dateType>
                <gmd:CI_DateTypeCode codeList="http://www.isotc211.org/2005/resources/Codelist/gmxCodelists.xml#CI_DateTypeCode" codeListValue="creation" codeSpace="ISOTC211/19115">creation</gmd:CI_DateTypeCode>
              </gmd:dateType>
            </gmd:CI_Date>
          </gmd:date>
          <gmd:date>
            <gmd:CI_Date>
              <gmd:date>
                <gco:Date>2015-01-07</gco:Date>
              </gmd:date>
              <gmd:dateType>
                <gmd:CI_DateTypeCode codeList="http://www.isotc211.org/2005/resources/Codelist/gmxCodelists.xml#CI_DateTypeCode" codeListValue="publication" codeSpace="ISOTC211/19115">publication</gmd:CI_DateTypeCode>
              </gmd:dateType>
            </gmd:CI_Date>
          </gmd:date>
          <gmd:citedResponsibleParty>
            <gmd:CI_ResponsibleParty>
              <gmd:individualName>
                <gco:CharacterString>Mark Solomon</gco:CharacterString>
              </gmd:individualName>
              <gmd:organisationName>
                <gco:CharacterString>Idaho Water Resources Research Institute</gco:CharacterString>
              </gmd:organisationName>
              <gmd:positionName>
                <gco:CharacterString>Water Research Scientist</gco:CharacterString>
              </gmd:positionName>
              <gmd:contactInfo>
                <gmd:CI_Contact>
                  <gmd:phone>
                    <gmd:CI_Telephone>
                      <gmd:voice>
                        <gco:CharacterString>(208) 664-7027</gco:CharacterString>
                      </gmd:voice>
                    </gmd:CI_Telephone>
                  </gmd:phone>
                  <gmd:address>
                    <gmd:CI_Address>
                      <gmd:electronicMailAddress>
                        <gco:CharacterString>msolomon@uidaho.edu</gco:CharacterString>
                      </gmd:electronicMailAddress>
                    </gmd:CI_Address>
                  </gmd:address>
                </gmd:CI_Contact>
              </gmd:contactInfo>
              <gmd:role>
                <gmd:CI_RoleCode codeList="http://www.isotc211.org/2005/resources/Codelist/gmxCodelists.xml#CI_RoleCode" codeListValue="pointOfContact" codeSpace="ISOTC211/19115">pointOfContact</gmd:CI_RoleCode>
              </gmd:role>
            </gmd:CI_ResponsibleParty>
          </gmd:citedResponsibleParty>
          <gmd:citedResponsibleParty>
            <gmd:CI_ResponsibleParty>
              <gmd:individualName>
                <gco:CharacterString>Michael Foushee</gco:CharacterString>
              </gmd:individualName>
              <gmd:organisationName>
                <gco:CharacterString>Idaho Water Resources Research Institute</gco:CharacterString>
              </gmd:organisationName>
              <gmd:positionName>
                <gco:CharacterString>GIS Analyst</gco:CharacterString>
              </gmd:positionName>
              <gmd:contactInfo>
                <gmd:CI_Contact>
                  <gmd:address>
                    <gmd:CI_Address>
                      <gmd:electronicMailAddress>
                        <gco:CharacterString>fous4241@vandals.uidaho.edu</gco:CharacterString>
                      </gmd:electronicMailAddress>
                    </gmd:CI_Address>
                  </gmd:address>
                </gmd:CI_Contact>
              </gmd:contactInfo>
              <gmd:role>
                <gmd:CI_RoleCode codeList="http://www.isotc211.org/2005/resources/Codelist/gmxCodelists.xml#CI_RoleCode" codeListValue="author" codeSpace="ISOTC211/19115">author</gmd:CI_RoleCode>
              </gmd:role>
            </gmd:CI_ResponsibleParty>
          </gmd:citedResponsibleParty>
          <gmd:citedResponsibleParty>
            <gmd:CI_ResponsibleParty>
              <gmd:organisationName>
                <gco:CharacterString>Idaho Water Resources Research Institute</gco:CharacterString>
              </gmd:organisationName>
              <gmd:role>
                <gmd:CI_RoleCode codeList="http://www.isotc211.org/2005/resources/Codelist/gmxCodelists.xml#CI_RoleCode" codeListValue="publisher" codeSpace="ISOTC211/19115">publisher</gmd:CI_RoleCode>
              </gmd:role>
            </gmd:CI_ResponsibleParty>
          </gmd:citedResponsibleParty>
        </gmd:CI_Citation>
      </gmd:citation>
      <gmd:abstract>
        <gco:CharacterString>Data used in the Rathdrum Prairie Aquifer Reasonably Anticipated Future
          Need (RAFN) study. Provides current and future service areas of water purveyors, city ACI,
          parcel data and land use data for the Rathdrum Prairie Aquifer RAFN study
          area.</gco:CharacterString>
      </gmd:abstract>
      <gmd:purpose>
        <gco:CharacterString>These data were created for the Rathdrum Prairie Aquifer Reasonably
          Anticipated Future Need study to aid in the analysis of current water demand, to assist in
          mediation of water boundaries, and to help plan for future water needs.
        </gco:CharacterString>
      </gmd:purpose>
      <gmd:credit>
        <gco:CharacterString>Idaho Water Resources Research Institute</gco:CharacterString>
      </gmd:credit>
      <gmd:pointOfContact>
        <gmd:CI_ResponsibleParty>
          <gmd:individualName>
            <gco:CharacterString>Mark Solomon</gco:CharacterString>
          </gmd:individualName>
          <gmd:organisationName>
            <gco:CharacterString>Idaho Water Resources Research Institute</gco:CharacterString>
          </gmd:organisationName>
          <gmd:positionName>
            <gco:CharacterString>Water Research Scientist</gco:CharacterString>
          </gmd:positionName>
          <gmd:contactInfo>
            <gmd:CI_Contact>
              <gmd:phone>
                <gmd:CI_Telephone>
                  <gmd:voice>
                    <gco:CharacterString>(208) 664-7027</gco:CharacterString>
                  </gmd:voice>
                </gmd:CI_Telephone>
              </gmd:phone>
              <gmd:address>
                <gmd:CI_Address>
                  <gmd:electronicMailAddress>
                    <gco:CharacterString>msolomon@uidaho.edu</gco:CharacterString>
                  </gmd:electronicMailAddress>
                </gmd:CI_Address>
              </gmd:address>
            </gmd:CI_Contact>
          </gmd:contactInfo>
          <gmd:role>
            <gmd:CI_RoleCode codeList="http://www.isotc211.org/2005/resources/Codelist/gmxCodelists.xml#CI_RoleCode" codeListValue="pointOfContact" codeSpace="ISOTC211/19115">pointOfContact</gmd:CI_RoleCode>
          </gmd:role>
        </gmd:CI_ResponsibleParty>
      </gmd:pointOfContact>
      <gmd:pointOfContact>
        <gmd:CI_ResponsibleParty>
          <gmd:individualName>
            <gco:CharacterString>Michael Foushee</gco:CharacterString>
          </gmd:individualName>
          <gmd:organisationName>
            <gco:CharacterString>Idaho Water Resources Research Institute</gco:CharacterString>
          </gmd:organisationName>
          <gmd:positionName>
            <gco:CharacterString>GIS Analyst</gco:CharacterString>
          </gmd:positionName>
          <gmd:contactInfo>
            <gmd:CI_Contact>
              <gmd:address>
                <gmd:CI_Address>
                  <gmd:electronicMailAddress>
                    <gco:CharacterString>fous4241@vandals.uidaho.edu</gco:CharacterString>
                  </gmd:electronicMailAddress>
                </gmd:CI_Address>
              </gmd:address>
            </gmd:CI_Contact>
          </gmd:contactInfo>
          <gmd:role>
            <gmd:CI_RoleCode codeList="http://www.isotc211.org/2005/resources/Codelist/gmxCodelists.xml#CI_RoleCode" codeListValue="author" codeSpace="ISOTC211/19115">author</gmd:CI_RoleCode>
          </gmd:role>
        </gmd:CI_ResponsibleParty>
      </gmd:pointOfContact>
      <gmd:descriptiveKeywords>
        <gmd:MD_Keywords>
          <gmd:keyword>
            <gco:CharacterString>rathdrum prairie</gco:CharacterString>
          </gmd:keyword>
          <gmd:keyword>
            <gco:CharacterString>rathdrum prairie aquifer</gco:CharacterString>
          </gmd:keyword>
          <gmd:keyword>
            <gco:CharacterString>kootenai</gco:CharacterString>
          </gmd:keyword>
          <gmd:keyword>
            <gco:CharacterString>bonner</gco:CharacterString>
          </gmd:keyword>
          <gmd:type>
            <gmd:MD_KeywordTypeCode codeList="http://www.isotc211.org/2005/resources/Codelist/gmxCodelists.xml#MD_KeywordTypeCode" codeListValue="place" codeSpace="ISOTC211/19115">place</gmd:MD_KeywordTypeCode>
          </gmd:type>
        </gmd:MD_Keywords>
      </gmd:descriptiveKeywords>
      <gmd:descriptiveKeywords>
        <gmd:MD_Keywords>
          <gmd:keyword>
            <gco:CharacterString>rafn</gco:CharacterString>
          </gmd:keyword>
          <gmd:keyword>
            <gco:CharacterString>water provider</gco:CharacterString>
          </gmd:keyword>
          <gmd:keyword>
            <gco:CharacterString>water purveyor</gco:CharacterString>
          </gmd:keyword>
          <gmd:keyword>
            <gco:CharacterString>water utility</gco:CharacterString>
          </gmd:keyword>
          <gmd:keyword>
            <gco:CharacterString>water service area</gco:CharacterString>
          </gmd:keyword>
          <gmd:keyword>
            <gco:CharacterString>utility service area</gco:CharacterString>
          </gmd:keyword>
          <gmd:keyword>
            <gco:CharacterString>aci</gco:CharacterString>
          </gmd:keyword>
          <gmd:keyword>
            <gco:CharacterString>parcel</gco:CharacterString>
          </gmd:keyword>
          <gmd:type>
            <gmd:MD_KeywordTypeCode codeList="http://www.isotc211.org/2005/resources/Codelist/gmxCodelists.xml#MD_KeywordTypeCode" codeListValue="theme" codeSpace="ISOTC211/19115">theme</gmd:MD_KeywordTypeCode>
          </gmd:type>
        </gmd:MD_Keywords>
      </gmd:descriptiveKeywords>
      <gmd:resourceConstraints>
        <gmd:MD_LegalConstraints>
          <gmd:accessConstraints>
            <gmd:MD_RestrictionCode codeList="http://www.isotc211.org/2005/resources/Codelist/gmxCodelists.xml#MD_RestrictionCode" codeListValue="otherRestrictions">otherRestrictions</gmd:MD_RestrictionCode>
          </gmd:accessConstraints>
          <gmd:useConstraints>
            <gmd:MD_RestrictionCode codeList="http://www.isotc211.org/2005/resources/Codelist/gmxCodelists.xml#MD_RestrictionCode" codeListValue="otherRestrictions">otherRestrictions</gmd:MD_RestrictionCode>
          </gmd:useConstraints>
          <gmd:otherConstraints>
            <gco:CharacterString>Access constraints: Data will be provided to all who agree to
              appropriately acknowledge the Idaho Water Resources Research Institute (IWRRI) and the
              individual investigators responsible for the data set. By downloading these data and
              using them to produce further analysis and/or products, users agree to appropriately
              acknowledge IWRRI and the individual investigators responsible for the data set. | Use
              constraints: Acceptable uses of data provided by IWRRI include any academic, research,
              educational, governmental, recreational, or other not-for-profit activities. Any use
              of data provided by IWRRI must acknowledge IWRRI and other identified source(s) that
              contributed to the collection of the data. Users are expected to inform IWRRI and the
              PI(s) responsible for the data of any work or publications based on data
              provided.</gco:CharacterString>
          </gmd:otherConstraints>
        </gmd:MD_LegalConstraints>
      </gmd:resourceConstraints>
      <gmd:language>
        <gmd:LanguageCode codeList="http://www.loc.gov/standards/iso639-2/php/code_list.php" codeListValue="eng" codeSpace="ISO639-2">eng</gmd:LanguageCode>
      </gmd:language>
      <gmd:characterSet>
        <gmd:MD_CharacterSetCode codeList="http://www.isotc211.org/2005/resources/Codelist/gmxCodelists.xml#MD_CharacterSetCode" codeListValue="utf8" codeSpace="ISOTC211/19115">utf8</gmd:MD_CharacterSetCode>
      </gmd:characterSet>
      <gmd:topicCategory>
        <gmd:MD_TopicCategoryCode>boundaries</gmd:MD_TopicCategoryCode>
      </gmd:topicCategory>
      <gmd:topicCategory>
        <gmd:MD_TopicCategoryCode>economy</gmd:MD_TopicCategoryCode>
      </gmd:topicCategory>
      <gmd:topicCategory>
        <gmd:MD_TopicCategoryCode>planningCadastre</gmd:MD_TopicCategoryCode>
      </gmd:topicCategory>
      <gmd:topicCategory>
        <gmd:MD_TopicCategoryCode>utilitiesCommunication</gmd:MD_TopicCategoryCode>
      </gmd:topicCategory>
      <gmd:extent>
        <gmd:EX_Extent>
          <gmd:description>
            <gco:CharacterString>Rathdrum Prairie Aquifer Reasonably Anticipated Future Need study
              area, encompassing portions of Kootenai and Bonner counties.</gco:CharacterString>
          </gmd:description>
          <gmd:geographicElement>
            <gmd:EX_GeographicBoundingBox>
              <gmd:westBoundLongitude>
                <gco:Decimal>-117.042222</gco:Decimal>
              </gmd:westBoundLongitude>
              <gmd:eastBoundLongitude>
                <gco:Decimal>-116.493963</gco:Decimal>
              </gmd:eastBoundLongitude>
              <gmd:southBoundLatitude>
                <gco:Decimal>47.57743</gco:Decimal>
              </gmd:southBoundLatitude>
              <gmd:northBoundLatitude>
                <gco:Decimal>48.081331</gco:Decimal>
              </gmd:northBoundLatitude>
            </gmd:EX_GeographicBoundingBox>
          </gmd:geographicElement>
        </gmd:EX_Extent>
      </gmd:extent>
      <gmd:extent>
        <gmd:EX_Extent>
          <gmd:geographicElement>
            <gmd:EX_GeographicBoundingBox>
              <gmd:westBoundLongitude>
                <gco:Decimal>-117.042222</gco:Decimal>
              </gmd:westBoundLongitude>
              <gmd:eastBoundLongitude>
                <gco:Decimal>-116.493963</gco:Decimal>
              </gmd:eastBoundLongitude>
              <gmd:southBoundLatitude>
                <gco:Decimal>47.57743</gco:Decimal>
              </gmd:southBoundLatitude>
              <gmd:northBoundLatitude>
                <gco:Decimal>48.081331</gco:Decimal>
              </gmd:northBoundLatitude>
            </gmd:EX_GeographicBoundingBox>
          </gmd:geographicElement>
        </gmd:EX_Extent>
      </gmd:extent>
    </gmd:MD_DataIdentification>
  </gmd:identificationInfo>
  <gmd:distributionInfo>
    <gmd:MD_Distribution>
      <gmd:distributor>
        <gmd:MD_Distributor>
          <gmd:distributorContact xlink:title="NKN">
            <gmd:CI_ResponsibleParty uuid="390bb26a-184d-4c30-8b3e-d74fe0783e28">
              <gmd:organisationName>
                <gco:CharacterString>Northwest Knowledge Network</gco:CharacterString>
              </gmd:organisationName>
              <gmd:contactInfo>
                <gmd:CI_Contact>
                  <gmd:phone>
                    <gmd:CI_Telephone>
                      <gmd:voice>
                        <gco:CharacterString>(208) 885-8456</gco:CharacterString>
                      </gmd:voice>
                    </gmd:CI_Telephone>
                  </gmd:phone>
                  <gmd:address>
                    <gmd:CI_Address>
                      <gmd:deliveryPoint>
                        <gco:CharacterString>University of Idaho Library</gco:CharacterString>
                      </gmd:deliveryPoint>
                      <gmd:deliveryPoint>
                        <gco:CharacterString>875 Perimeter Drive, MS 2358</gco:CharacterString>
                      </gmd:deliveryPoint>
                      <gmd:city>
                        <gco:CharacterString>Moscow</gco:CharacterString>
                      </gmd:city>
                      <gmd:administrativeArea>
                        <gco:CharacterString>ID</gco:CharacterString>
                      </gmd:administrativeArea>
                      <gmd:postalCode>
                        <gco:CharacterString>83844-2350</gco:CharacterString>
                      </gmd:postalCode>
                      <gmd:country>
                        <gco:CharacterString>USA</gco:CharacterString>
                      </gmd:country>
                      <gmd:electronicMailAddress>
                        <gco:CharacterString>info@northwestknowledge.net</gco:CharacterString>
                      </gmd:electronicMailAddress>
                    </gmd:CI_Address>
                  </gmd:address>
                  <gmd:onlineResource>
                    <gmd:CI_OnlineResource>
                      <gmd:linkage>
                        <gmd:URL>https://www.northwestknowledge.net/</gmd:URL>
                      </gmd:linkage>
                      <gmd:name>
                        <gco:CharacterString>The home page for the Northwest Knowledge Network</gco:CharacterString>
                      </gmd:name>
                    </gmd:CI_OnlineResource>
                  </gmd:onlineResource>
                </gmd:CI_Contact>
              </gmd:contactInfo>
              <gmd:role>
                <gmd:CI_RoleCode codeList="http://www.isotc211.org/2005/resources/Codelist/gmxCodelists.xml#CI_RoleCode" codeListValue="distributor">distributor</gmd:CI_RoleCode>
              </gmd:role>
            </gmd:CI_ResponsibleParty>
          </gmd:distributorContact>
          <gmd:distributorFormat>
            <gmd:MD_Format>
              <gmd:name>
                <gco:CharacterString>Esri Shape File (SHP)</gco:CharacterString>
              </gmd:name>
              <gmd:version>
                <gco:CharacterString>Esri ArcGIS 10.2.2.3552</gco:CharacterString>
              </gmd:version>
              <gmd:fileDecompressionTechnique>
                <gco:CharacterString>The shape files are compressed in standard ZIP format.</gco:CharacterString>
              </gmd:fileDecompressionTechnique>
            </gmd:MD_Format>
          </gmd:distributorFormat>
          <gmd:distributorTransferOptions>
            <gmd:MD_DigitalTransferOptions>
              <gmd:transferSize>
                <gco:Real>5.11</gco:Real>
              </gmd:transferSize>
              <gmd:onLine>
                <gmd:CI_OnlineResource>
                  <gmd:linkage>
                    <gmd:URL>https://www.northwestknowledge.net/data/download.php?uuid=d986d1f3-89c1-4c76-9946-eb750f3e921a</gmd:URL>
                  </gmd:linkage>
                  <gmd:function>
                    <gmd:CI_OnLineFunctionCode codeList="http://www.isotc211.org/2005/resources/Codelist/gmxCodelists.xml#CI_OnLineFunctionCode" codeListValue="download">download</gmd:CI_OnLineFunctionCode>
                  </gmd:function>
                </gmd:CI_OnlineResource>
              </gmd:onLine>
            </gmd:MD_DigitalTransferOptions>
          </gmd:distributorTransferOptions>
          <gmd:distributorTransferOptions>
            <gmd:MD_DigitalTransferOptions>
              <gmd:onLine>
                <gmd:CI_OnlineResource>
                  <gmd:linkage>
                    <gmd:URL>https://www.northwestknowledge.net/</gmd:URL>
                  </gmd:linkage>
                  <gmd:function>
                    <gmd:CI_OnLineFunctionCode codeList="http://www.isotc211.org/2005/resources/Codelist/gmxCodelists.xml#CI_OnLineFunctionCode" codeListValue="search">search</gmd:CI_OnLineFunctionCode>
                  </gmd:function>
                </gmd:CI_OnlineResource>
              </gmd:onLine>
            </gmd:MD_DigitalTransferOptions>
          </gmd:distributorTransferOptions>
        </gmd:MD_Distributor>
      </gmd:distributor>
      <gmd:distributor>
        <gmd:MD_Distributor>
          <gmd:distributorContact>
            <gmd:CI_ResponsibleParty>
              <gmd:organisationName>
                <gco:CharacterString>University of Idaho Library</gco:CharacterString>
              </gmd:organisationName>
              <gmd:contactInfo>
                <gmd:CI_Contact>
                  <gmd:phone>
                    <gmd:CI_Telephone>
                      <gmd:voice>
                        <gco:CharacterString>(208) 885-6559</gco:CharacterString>
                      </gmd:voice>
                    </gmd:CI_Telephone>
                  </gmd:phone>
                  <gmd:address>
                    <gmd:CI_Address>
                      <gmd:deliveryPoint>
                        <gco:CharacterString>University of Idaho Library</gco:CharacterString>
                      </gmd:deliveryPoint>
                      <gmd:deliveryPoint>
                        <gco:CharacterString>875 Perimeter Dr. MS 2350</gco:CharacterString>
                      </gmd:deliveryPoint>
                      <gmd:city>
                        <gco:CharacterString>Moscow</gco:CharacterString>
                      </gmd:city>
                      <gmd:administrativeArea>
                        <gco:CharacterString>ID</gco:CharacterString>
                      </gmd:administrativeArea>
                      <gmd:postalCode>
                        <gco:CharacterString>83844-2350</gco:CharacterString>
                      </gmd:postalCode>
                      <gmd:country>
                        <gco:CharacterString>USA</gco:CharacterString>
                      </gmd:country>
                      <gmd:electronicMailAddress>
                        <gco:CharacterString>libref@uidaho.edu </gco:CharacterString>
                      </gmd:electronicMailAddress>
                    </gmd:CI_Address>
                  </gmd:address>
                  <gmd:onlineResource>
                    <gmd:CI_OnlineResource>
                      <gmd:linkage>
                        <gmd:URL>http://www.lib.uidaho.edu/</gmd:URL>
                      </gmd:linkage>
                      <gmd:name>
                        <gco:CharacterString>The home page for the Univeristy of Idaho Library</gco:CharacterString>
                      </gmd:name>
                    </gmd:CI_OnlineResource>
                  </gmd:onlineResource>
                </gmd:CI_Contact>
              </gmd:contactInfo>
              <gmd:role>
                <gmd:CI_RoleCode codeList="http://www.isotc211.org/2005/resources/Codelist/gmxCodelists.xml#CI_RoleCode" codeListValue="distributor">distributor</gmd:CI_RoleCode>
              </gmd:role>
            </gmd:CI_ResponsibleParty>
          </gmd:distributorContact>
          <gmd:distributorFormat>
            <gmd:MD_Format>
              <gmd:name>
                <gco:CharacterString>Portable Document Format (pdf)</gco:CharacterString>
              </gmd:name>
              <gmd:version>
                <gco:CharacterString>PDF Version 1.5 (Acrobat 6.x)</gco:CharacterString>
              </gmd:version>
            </gmd:MD_Format>
          </gmd:distributorFormat>
          <gmd:distributorTransferOptions>
            <gmd:MD_DigitalTransferOptions>
              <gmd:onLine>
                <gmd:CI_OnlineResource>
                  <gmd:linkage>
                    <gmd:URL>http://digital.lib.uidaho.edu/cdm/ref/collection/idahowater/id/546</gmd:URL>
                  </gmd:linkage>
                  <gmd:function>
                    <gmd:CI_OnLineFunctionCode codeList="http://www.isotc211.org/2005/resources/Codelist/gmxCodelists.xml#CI_OnLineFunctionCode" codeListValue="information">information</gmd:CI_OnLineFunctionCode>
                  </gmd:function>
                </gmd:CI_OnlineResource>
              </gmd:onLine>
            </gmd:MD_DigitalTransferOptions>
          </gmd:distributorTransferOptions>  
        </gmd:MD_Distributor>
      </gmd:distributor>
    </gmd:MD_Distribution>
  </gmd:distributionInfo>
</gmd:MD_Metadata>